[{"model": "user.district", "pk": 15, "fields": {"title": "Amudaryo tumani", "region": 1, "sort": 1, "is_active": true}}, {"model": "user.district", "pk": 16, "fields": {"title": "Beruniy tumani", "region": 1, "sort": 1, "is_active": true}}, {"model": "user.district", "pk": 17, "fields": {"title": "Kegayli tumani", "region": 1, "sort": 1, "is_active": true}}, {"model": "user.district", "pk": 18, "fields": {"title": "Qonlikoæl tumani", "region": 1, "sort": 1, "is_active": true}}, {"model": "user.district", "pk": 19, "fields": {"title": "Qoraoæzak tumani", "region": 1, "sort": 1, "is_active": true}}, {"model": "user.district", "pk": 20, "fields": {"title": "Qoængæirot tumani", "region": 1, "sort": 1, "is_active": true}}, {"model": "user.district", "pk": 21, "fields": {"title": "Moæynoq tumani", "region": 1, "sort": 1, "is_active": true}}, {"model": "user.district", "pk": 22, "fields": {"title": "Nukus tumani", "region": 1, "sort": 1, "is_active": true}}, {"model": "user.district", "pk": 23, "fields": {"title": "Nukus shahri", "region": 1, "sort": 1, "is_active": true}}, {"model": "user.district", "pk": 24, "fields": {"title": "Taxtakoæpir tumani", "region": 1, "sort": 1, "is_active": true}}, {"model": "user.district", "pk": 25, "fields": {"title": "Toærtkoæl tumani", "region": 1, "sort": 1, "is_active": true}}, {"model": "user.district", "pk": 26, "fields": {"title": "Xoæjayli tumani", "region": 1, "sort": 1, "is_active": true}}, {"model": "user.district", "pk": 27, "fields": {"title": "CHimboy tumani", "region": 1, "sort": 1, "is_active": true}}, {"model": "user.district", "pk": 28, "fields": {"title": "SHumanay tumani", "region": 1, "sort": 1, "is_active": true}}, {"model": "user.district", "pk": 29, "fields": {"title": "Ellikqalæa tumani", "region": 1, "sort": 1, "is_active": true}}, {"model": "user.district", "pk": 30, "fields": {"title": "Andijon shahri", "region": 2, "sort": 1, "is_active": true}}, {"model": "user.district", "pk": 31, "fields": {"title": "Andijon tumani", "region": 2, "sort": 1, "is_active": true}}, {"model": "user.district", "pk": 32, "fields": {"title": "Asaka tumani", "region": 2, "sort": 1, "is_active": true}}, {"model": "user.district", "pk": 33, "fields": {"title": "Baliqchi tumani", "region": 2, "sort": 1, "is_active": true}}, {"model": "user.district", "pk": 34, "fields": {"title": "Buloqboshi tumani", "region": 2, "sort": 1, "is_active": true}}, {"model": "user.district", "pk": 35, "fields": {"title": "Boæz tumani", "region": 2, "sort": 1, "is_active": true}}, {"model": "user.district", "pk": 36, "fields": {"title": "Jalaquduq tumani", "region": 2, "sort": 1, "is_active": true}}, {"model": "user.district", "pk": 37, "fields": {"title": "Izbosgan tumani", "region": 2, "sort": 1, "is_active": true}}, {"model": "user.district", "pk": 38, "fields": {"title": "Qorasuv shahri", "region": 2, "sort": 1, "is_active": true}}, {"model": "user.district", "pk": 39, "fields": {"title": "Qoærgæontepa tumani", "region": 2, "sort": 1, "is_active": true}}, {"model": "user.district", "pk": 40, "fields": {"title": "Marhamat tumani", "region": 2, "sort": 1, "is_active": true}}, {"model": "user.district", "pk": 41, "fields": {"title": "Oltinkoæl tumani", "region": 2, "sort": 1, "is_active": true}}, {"model": "user.district", "pk": 42, "fields": {"title": "Paxtaobod tumani", "region": 2, "sort": 1, "is_active": true}}, {"model": "user.district", "pk": 43, "fields": {"title": "Ulugænor tumani", "region": 2, "sort": 1, "is_active": true}}, {"model": "user.district", "pk": 44, "fields": {"title": "Xonabod tumani", "region": 2, "sort": 1, "is_active": true}}, {"model": "user.district", "pk": 45, "fields": {"title": "Xoæjaobod shahri", "region": 2, "sort": 1, "is_active": true}}, {"model": "user.district", "pk": 46, "fields": {"title": "Shaxrixon tumani", "region": 2, "sort": 1, "is_active": true}}, {"model": "user.district", "pk": 47, "fields": {"title": "Buxoro shahri", "region": 3, "sort": 1, "is_active": true}}, {"model": "user.district", "pk": 48, "fields": {"title": "Buxoro tumani", "region": 3, "sort": 1, "is_active": true}}, {"model": "user.district", "pk": 49, "fields": {"title": "Vobkent tumani", "region": 3, "sort": 1, "is_active": true}}, {"model": "user.district", "pk": 50, "fields": {"title": "Gæijduvon tumani", "region": 3, "sort": 1, "is_active": true}}, {"model": "user.district", "pk": 51, "fields": {"title": "Jondor tumani", "region": 3, "sort": 1, "is_active": true}}, {"model": "user.district", "pk": 52, "fields": {"title": "Kogon tumani", "region": 3, "sort": 1, "is_active": true}}, {"model": "user.district", "pk": 53, "fields": {"title": "Kogon shahri", "region": 3, "sort": 1, "is_active": true}}, {"model": "user.district", "pk": 54, "fields": {"title": "Qorakoæl tumani", "region": 3, "sort": 1, "is_active": true}}, {"model": "user.district", "pk": 55, "fields": {"title": "Qorovulbozor tumani", "region": 3, "sort": 1, "is_active": true}}, {"model": "user.district", "pk": 56, "fields": {"title": "Olot tumani", "region": 3, "sort": 1, "is_active": true}}, {"model": "user.district", "pk": 57, "fields": {"title": "Peshku tumani", "region": 3, "sort": 1, "is_active": true}}, {"model": "user.district", "pk": 58, "fields": {"title": "Romitan tumani", "region": 3, "sort": 1, "is_active": true}}, {"model": "user.district", "pk": 59, "fields": {"title": "Shofirkon tumani", "region": 3, "sort": 1, "is_active": true}}, {"model": "user.district", "pk": 60, "fields": {"title": "Arnasoy tumani", "region": 4, "sort": 1, "is_active": true}}, {"model": "user.district", "pk": 61, "fields": {"title": "Baxmal tumani", "region": 4, "sort": 1, "is_active": true}}, {"model": "user.district", "pk": 62, "fields": {"title": "Gæallaorol tumani", "region": 4, "sort": 1, "is_active": true}}, {"model": "user.district", "pk": 63, "fields": {"title": "Doæstlik tumani", "region": 4, "sort": 1, "is_active": true}}, {"model": "user.district", "pk": 64, "fields": {"title": "Sh.Rashidov tumani", "region": 4, "sort": 1, "is_active": true}}, {"model": "user.district", "pk": 65, "fields": {"title": "Jizzax shahri", "region": 4, "sort": 1, "is_active": true}}, {"model": "user.district", "pk": 66, "fields": {"title": "Zarbdor tumani", "region": 4, "sort": 1, "is_active": true}}, {"model": "user.district", "pk": 67, "fields": {"title": "Zafarobod tumani", "region": 4, "sort": 1, "is_active": true}}, {"model": "user.district", "pk": 68, "fields": {"title": "Zomin tumani", "region": 4, "sort": 1, "is_active": true}}, {"model": "user.district", "pk": 69, "fields": {"title": "Mirzachoæl tumani", "region": 4, "sort": 1, "is_active": true}}, {"model": "user.district", "pk": 70, "fields": {"title": "Paxtakor tumani", "region": 4, "sort": 1, "is_active": true}}, {"model": "user.district", "pk": 71, "fields": {"title": "Forish tumani", "region": 4, "sort": 1, "is_active": true}}, {"model": "user.district", "pk": 72, "fields": {"title": "Yangiobod tumani", "region": 4, "sort": 1, "is_active": true}}, {"model": "user.district", "pk": 73, "fields": {"title": "Gæuzor tumani", "region": 5, "sort": 1, "is_active": true}}, {"model": "user.district", "pk": 74, "fields": {"title": "Dehqonobod tumani", "region": 5, "sort": 1, "is_active": true}}, {"model": "user.district", "pk": 75, "fields": {"title": "Qamashi tumani", "region": 5, "sort": 1, "is_active": true}}, {"model": "user.district", "pk": 76, "fields": {"title": "Qarshi tumani", "region": 5, "sort": 1, "is_active": true}}, {"model": "user.district", "pk": 77, "fields": {"title": "Qarshi shahri", "region": 5, "sort": 1, "is_active": true}}, {"model": "user.district", "pk": 78, "fields": {"title": "Kasbi tumani", "region": 5, "sort": 1, "is_active": true}}, {"model": "user.district", "pk": 79, "fields": {"title": "Kitob tumani", "region": 5, "sort": 1, "is_active": true}}, {"model": "user.district", "pk": 80, "fields": {"title": "Koson tumani", "region": 5, "sort": 1, "is_active": true}}, {"model": "user.district", "pk": 81, "fields": {"title": "Mirishkor tumani", "region": 5, "sort": 1, "is_active": true}}, {"model": "user.district", "pk": 82, "fields": {"title": "Muborak tumani", "region": 5, "sort": 1, "is_active": true}}, {"model": "user.district", "pk": 83, "fields": {"title": "Nishon tumani", "region": 5, "sort": 1, "is_active": true}}, {"model": "user.district", "pk": 84, "fields": {"title": "Chiroqchi tumani", "region": 5, "sort": 1, "is_active": true}}, {"model": "user.district", "pk": 85, "fields": {"title": "Shahrisabz tumani", "region": 5, "sort": 1, "is_active": true}}, {"model": "user.district", "pk": 86, "fields": {"title": "Yakkabogæ tumani", "region": 5, "sort": 1, "is_active": true}}, {"model": "user.district", "pk": 87, "fields": {"title": "Zarafshon shahri", "region": 6, "sort": 1, "is_active": true}}, {"model": "user.district", "pk": 88, "fields": {"title": "Karmana tumani", "region": 6, "sort": 1, "is_active": true}}, {"model": "user.district", "pk": 89, "fields": {"title": "Qiziltepa tumani", "region": 6, "sort": 1, "is_active": true}}, {"model": "user.district", "pk": 90, "fields": {"title": "Konimex tumani", "region": 6, "sort": 1, "is_active": true}}, {"model": "user.district", "pk": 91, "fields": {"title": "Navbahor tumani", "region": 6, "sort": 1, "is_active": true}}, {"model": "user.district", "pk": 92, "fields": {"title": "Navoiy shahri", "region": 6, "sort": 1, "is_active": true}}, {"model": "user.district", "pk": 93, "fields": {"title": "Nurota tumani", "region": 6, "sort": 1, "is_active": true}}, {"model": "user.district", "pk": 94, "fields": {"title": "Tomdi tumani", "region": 6, "sort": 1, "is_active": true}}, {"model": "user.district", "pk": 95, "fields": {"title": "Uchquduq tumani", "region": 6, "sort": 1, "is_active": true}}, {"model": "user.district", "pk": 96, "fields": {"title": "Xatirchi tumani", "region": 6, "sort": 1, "is_active": true}}, {"model": "user.district", "pk": 97, "fields": {"title": "Kosonsoy tumani", "region": 7, "sort": 1, "is_active": true}}, {"model": "user.district", "pk": 98, "fields": {"title": "Mingbuloq tumani", "region": 7, "sort": 1, "is_active": true}}, {"model": "user.district", "pk": 99, "fields": {"title": "Namangan tumani", "region": 7, "sort": 1, "is_active": true}}, {"model": "user.district", "pk": 100, "fields": {"title": "Namangan shahri", "region": 7, "sort": 1, "is_active": true}}, {"model": "user.district", "pk": 101, "fields": {"title": "Norin tumani", "region": 7, "sort": 1, "is_active": true}}, {"model": "user.district", "pk": 102, "fields": {"title": "Pop tumani", "region": 7, "sort": 1, "is_active": true}}, {"model": "user.district", "pk": 103, "fields": {"title": "Toæraqoærgæon tumani", "region": 7, "sort": 1, "is_active": true}}, {"model": "user.district", "pk": 104, "fields": {"title": "Uychi tumani", "region": 7, "sort": 1, "is_active": true}}, {"model": "user.district", "pk": 105, "fields": {"title": "Uchqoærgæon tumani", "region": 7, "sort": 1, "is_active": true}}, {"model": "user.district", "pk": 106, "fields": {"title": "Chortoq tumani", "region": 7, "sort": 1, "is_active": true}}, {"model": "user.district", "pk": 107, "fields": {"title": "Chust tumani", "region": 7, "sort": 1, "is_active": true}}, {"model": "user.district", "pk": 108, "fields": {"title": "Yangiqoærgæon tumani", "region": 7, "sort": 1, "is_active": true}}, {"model": "user.district", "pk": 109, "fields": {"title": "Bulungæur tumani", "region": 8, "sort": 1, "is_active": true}}, {"model": "user.district", "pk": 110, "fields": {"title": "Jomboy tumani", "region": 8, "sort": 1, "is_active": true}}, {"model": "user.district", "pk": 111, "fields": {"title": "Ishtixon tumani", "region": 8, "sort": 1, "is_active": true}}, {"model": "user.district", "pk": 112, "fields": {"title": "Kattaqoærgæon tumani", "region": 8, "sort": 1, "is_active": true}}, {"model": "user.district", "pk": 113, "fields": {"title": "Kattaqoærgæon shahri", "region": 8, "sort": 1, "is_active": true}}, {"model": "user.district", "pk": 114, "fields": {"title": "Qoæshrabot tumani", "region": 8, "sort": 1, "is_active": true}}, {"model": "user.district", "pk": 115, "fields": {"title": "Narpay tumani", "region": 8, "sort": 1, "is_active": true}}, {"model": "user.district", "pk": 116, "fields": {"title": "Nurabod tumani", "region": 8, "sort": 1, "is_active": true}}, {"model": "user.district", "pk": 117, "fields": {"title": "Oqdaryo tumani", "region": 8, "sort": 1, "is_active": true}}, {"model": "user.district", "pk": 118, "fields": {"title": "Payariq tumani", "region": 8, "sort": 1, "is_active": true}}, {"model": "user.district", "pk": 119, "fields": {"title": "Pastargæom tumani", "region": 8, "sort": 1, "is_active": true}}, {"model": "user.district", "pk": 120, "fields": {"title": "Paxtachi tumani", "region": 8, "sort": 1, "is_active": true}}, {"model": "user.district", "pk": 121, "fields": {"title": "Samarqand tumani", "region": 8, "sort": 1, "is_active": true}}, {"model": "user.district", "pk": 122, "fields": {"title": "Samarqand shahri", "region": 8, "sort": 1, "is_active": true}}, {"model": "user.district", "pk": 123, "fields": {"title": "Toyloq tumani", "region": 8, "sort": 1, "is_active": true}}, {"model": "user.district", "pk": 124, "fields": {"title": "Urgut tumani", "region": 8, "sort": 1, "is_active": true}}, {"model": "user.district", "pk": 125, "fields": {"title": "Angor tumani", "region": 9, "sort": 1, "is_active": true}}, {"model": "user.district", "pk": 126, "fields": {"title": "Boysun tumani", "region": 9, "sort": 1, "is_active": true}}, {"model": "user.district", "pk": 127, "fields": {"title": "Denov tumani", "region": 9, "sort": 1, "is_active": true}}, {"model": "user.district", "pk": 128, "fields": {"title": "Jarqoærgæon tumani", "region": 9, "sort": 1, "is_active": true}}, {"model": "user.district", "pk": 129, "fields": {"title": "Qiziriq tumani", "region": 9, "sort": 1, "is_active": true}}, {"model": "user.district", "pk": 130, "fields": {"title": "Qoæmqoærgæon tumani", "region": 9, "sort": 1, "is_active": true}}, {"model": "user.district", "pk": 131, "fields": {"title": "Muzrabot tumani", "region": 9, "sort": 1, "is_active": true}}, {"model": "user.district", "pk": 132, "fields": {"title": "Oltinsoy tumani", "region": 9, "sort": 1, "is_active": true}}, {"model": "user.district", "pk": 133, "fields": {"title": "Sariosiy tumani", "region": 9, "sort": 1, "is_active": true}}, {"model": "user.district", "pk": 134, "fields": {"title": "Termiz tumani", "region": 9, "sort": 1, "is_active": true}}, {"model": "user.district", "pk": 135, "fields": {"title": "Termiz shahri", "region": 9, "sort": 1, "is_active": true}}, {"model": "user.district", "pk": 136, "fields": {"title": "Uzun tumani", "region": 9, "sort": 1, "is_active": true}}, {"model": "user.district", "pk": 137, "fields": {"title": "Sherobod tumani", "region": 9, "sort": 1, "is_active": true}}, {"model": "user.district", "pk": 138, "fields": {"title": "Shoærchi tumani", "region": 9, "sort": 1, "is_active": true}}, {"model": "user.district", "pk": 139, "fields": {"title": "Boyovut tumani", "region": 10, "sort": 1, "is_active": true}}, {"model": "user.district", "pk": 140, "fields": {"title": "Guliston tumani", "region": 10, "sort": 1, "is_active": true}}, {"model": "user.district", "pk": 141, "fields": {"title": "Guliston shahri", "region": 10, "sort": 1, "is_active": true}}, {"model": "user.district", "pk": 142, "fields": {"title": "Mirzaobod tumani", "region": 10, "sort": 1, "is_active": true}}, {"model": "user.district", "pk": 143, "fields": {"title": "Oqoltin tumani", "region": 10, "sort": 1, "is_active": true}}, {"model": "user.district", "pk": 144, "fields": {"title": "Sayxunobod tumani", "region": 10, "sort": 1, "is_active": true}}, {"model": "user.district", "pk": 145, "fields": {"title": "Sardoba tumani", "region": 10, "sort": 1, "is_active": true}}, {"model": "user.district", "pk": 146, "fields": {"title": "Sirdaryo tumani", "region": 10, "sort": 1, "is_active": true}}, {"model": "user.district", "pk": 147, "fields": {"title": "Xavos tumani", "region": 10, "sort": 1, "is_active": true}}, {"model": "user.district", "pk": 148, "fields": {"title": "Shirin shahri", "region": 10, "sort": 1, "is_active": true}}, {"model": "user.district", "pk": 149, "fields": {"title": "Yangier shahri", "region": 10, "sort": 1, "is_active": true}}, {"model": "user.district", "pk": 150, "fields": {"title": "Angiren shahri", "region": 11, "sort": 1, "is_active": true}}, {"model": "user.district", "pk": 151, "fields": {"title": "Bekabod tumani", "region": 11, "sort": 1, "is_active": true}}, {"model": "user.district", "pk": 152, "fields": {"title": "Bekabod shahri", "region": 11, "sort": 1, "is_active": true}}, {"model": "user.district", "pk": 153, "fields": {"title": "Boæka tumani", "region": 11, "sort": 1, "is_active": true}}, {"model": "user.district", "pk": 154, "fields": {"title": "Boæstonliq tumani", "region": 11, "sort": 1, "is_active": true}}, {"model": "user.district", "pk": 155, "fields": {"title": "Zangiota tumani", "region": 11, "sort": 1, "is_active": true}}, {"model": "user.district", "pk": 156, "fields": {"title": "Qibray tumani", "region": 11, "sort": 1, "is_active": true}}, {"model": "user.district", "pk": 157, "fields": {"title": "Quyichirchiq tumani", "region": 11, "sort": 1, "is_active": true}}, {"model": "user.district", "pk": 158, "fields": {"title": "Oqqoærgæon tumani", "region": 11, "sort": 1, "is_active": true}}, {"model": "user.district", "pk": 159, "fields": {"title": "Olmaliq shahri", "region": 11, "sort": 1, "is_active": true}}, {"model": "user.district", "pk": 160, "fields": {"title": "Ohangaron tumani", "region": 11, "sort": 1, "is_active": true}}, {"model": "user.district", "pk": 161, "fields": {"title": "Parkent tumani", "region": 11, "sort": 1, "is_active": true}}, {"model": "user.district", "pk": 162, "fields": {"title": "Piskent tumani", "region": 11, "sort": 1, "is_active": true}}, {"model": "user.district", "pk": 163, "fields": {"title": "Oærtachirchiq tumani", "region": 11, "sort": 1, "is_active": true}}, {"model": "user.district", "pk": 164, "fields": {"title": "Chinoz tumani", "region": 11, "sort": 1, "is_active": true}}, {"model": "user.district", "pk": 165, "fields": {"title": "Chirchiq shahri", "region": 11, "sort": 1, "is_active": true}}, {"model": "user.district", "pk": 166, "fields": {"title": "Yuqorichirchiq tumani", "region": 11, "sort": 1, "is_active": true}}, {"model": "user.district", "pk": 167, "fields": {"title": "Yangiyoæl tumani", "region": 11, "sort": 1, "is_active": true}}, {"model": "user.district", "pk": 168, "fields": {"title": "Beshariq tumani", "region": 12, "sort": 1, "is_active": true}}, {"model": "user.district", "pk": 169, "fields": {"title": "Bogædod tumani", "region": 12, "sort": 1, "is_active": true}}, {"model": "user.district", "pk": 170, "fields": {"title": "Buvayda tumani", "region": 12, "sort": 1, "is_active": true}}, {"model": "user.district", "pk": 171, "fields": {"title": "Dangæara tumani", "region": 12, "sort": 1, "is_active": true}}, {"model": "user.district", "pk": 172, "fields": {"title": "Yozyovon tumani", "region": 12, "sort": 1, "is_active": true}}, {"model": "user.district", "pk": 173, "fields": {"title": "Quva tumani", "region": 12, "sort": 1, "is_active": true}}, {"model": "user.district", "pk": 174, "fields": {"title": "Quvasoy shahri", "region": 12, "sort": 1, "is_active": true}}, {"model": "user.district", "pk": 175, "fields": {"title": "Qoæqon shahri", "region": 12, "sort": 1, "is_active": true}}, {"model": "user.district", "pk": 176, "fields": {"title": "Qoæshtepa tumani", "region": 12, "sort": 1, "is_active": true}}, {"model": "user.district", "pk": 177, "fields": {"title": "Margæilon shahri", "region": 12, "sort": 1, "is_active": true}}, {"model": "user.district", "pk": 178, "fields": {"title": "Oltiariq tumani", "region": 12, "sort": 1, "is_active": true}}, {"model": "user.district", "pk": 179, "fields": {"title": "Rishton tumani", "region": 12, "sort": 1, "is_active": true}}, {"model": "user.district", "pk": 180, "fields": {"title": "Soæx tumani", "region": 12, "sort": 1, "is_active": true}}, {"model": "user.district", "pk": 181, "fields": {"title": "Toshloq tumani", "region": 12, "sort": 1, "is_active": true}}, {"model": "user.district", "pk": 182, "fields": {"title": "Uchkoæprik tumani", "region": 12, "sort": 1, "is_active": true}}, {"model": "user.district", "pk": 183, "fields": {"title": "Oæzbekiston tumani", "region": 12, "sort": 1, "is_active": true}}, {"model": "user.district", "pk": 184, "fields": {"title": "Fargæona tumani", "region": 12, "sort": 1, "is_active": true}}, {"model": "user.district", "pk": 185, "fields": {"title": "Fargæona shahri", "region": 12, "sort": 1, "is_active": true}}, {"model": "user.district", "pk": 186, "fields": {"title": "Furqat tumani", "region": 12, "sort": 1, "is_active": true}}, {"model": "user.district", "pk": 187, "fields": {"title": "Bogæot tumani", "region": 13, "sort": 1, "is_active": true}}, {"model": "user.district", "pk": 188, "fields": {"title": "Gurlan tumani", "region": 13, "sort": 1, "is_active": true}}, {"model": "user.district", "pk": 189, "fields": {"title": "Qoæshkoæpir tumani", "region": 13, "sort": 1, "is_active": true}}, {"model": "user.district", "pk": 190, "fields": {"title": "Urganch tumani", "region": 13, "sort": 1, "is_active": true}}, {"model": "user.district", "pk": 191, "fields": {"title": "Urganch shahri", "region": 13, "sort": 1, "is_active": true}}, {"model": "user.district", "pk": 192, "fields": {"title": "Xiva tumani", "region": 13, "sort": 1, "is_active": true}}, {"model": "user.district", "pk": 193, "fields": {"title": "Xazarasp tumani", "region": 13, "sort": 1, "is_active": true}}, {"model": "user.district", "pk": 194, "fields": {"title": "Xonqa tumani", "region": 13, "sort": 1, "is_active": true}}, {"model": "user.district", "pk": 195, "fields": {"title": "Shavot tumani", "region": 13, "sort": 1, "is_active": true}}, {"model": "user.district", "pk": 196, "fields": {"title": "Yangiariq tumani", "region": 13, "sort": 1, "is_active": true}}, {"model": "user.district", "pk": 197, "fields": {"title": "Yangibozor tumani", "region": 13, "sort": 1, "is_active": true}}, {"model": "user.district", "pk": 198, "fields": {"title": "Bektimer tumani", "region": 14, "sort": 1, "is_active": true}}, {"model": "user.district", "pk": 199, "fields": {"title": "M.Ulugæbek tumani", "region": 14, "sort": 1, "is_active": true}}, {"model": "user.district", "pk": 200, "fields": {"title": "Mirobod tumani", "region": 14, "sort": 1, "is_active": true}}, {"model": "user.district", "pk": 201, "fields": {"title": "Olmazor tumani", "region": 14, "sort": 1, "is_active": true}}, {"model": "user.district", "pk": 202, "fields": {"title": "Sergeli tumani", "region": 14, "sort": 1, "is_active": true}}, {"model": "user.district", "pk": 203, "fields": {"title": "Uchtepa tumani", "region": 14, "sort": 1, "is_active": true}}, {"model": "user.district", "pk": 204, "fields": {"title": "Yashnobod tumani", "region": 14, "sort": 1, "is_active": true}}, {"model": "user.district", "pk": 205, "fields": {"title": "Chilonzor tumani", "region": 14, "sort": 1, "is_active": true}}, {"model": "user.district", "pk": 206, "fields": {"title": "Shayxontohur tumani", "region": 14, "sort": 1, "is_active": true}}, {"model": "user.district", "pk": 207, "fields": {"title": "Yunusobod tumani", "region": 14, "sort": 1, "is_active": true}}, {"model": "user.district", "pk": 208, "fields": {"title": "Yakkasaroy tumani", "region": 14, "sort": 1, "is_active": true}}, {"model": "user.district", "pk": 209, "fields": {"title": "Taxiatosh shahri", "region": 1, "sort": 1, "is_active": true}}, {"model": "user.district", "pk": 210, "fields": {"title": "Asaka shahri", "region": 2, "sort": 1, "is_active": true}}, {"model": "user.district", "pk": 211, "fields": {"title": "Bandixon tumani", "region": 9, "sort": 1, "is_active": true}}, {"model": "user.district", "pk": 212, "fields": {"title": "Ohangaron shahri", "region": 11, "sort": 1, "is_active": true}}, {"model": "user.district", "pk": 213, "fields": {"title": "Yangiyoæl shahri", "region": 11, "sort": 1, "is_active": true}}, {"model": "user.district", "pk": 215, "fields": {"title": "Toshkent tumani", "region": 11, "sort": 1, "is_active": true}}]
